{
  "type": "vstack",
  "neverRecomputeExistingPartitions": false,
  "optionalDependencies": false,
  "customMeta": {
    "kv": {}
  },
  "redispatchPartitioning": false,
  "maxRunningActivities": 0,
  "inputs": {
    "main": {
      "items": [
        {
          "ref": "proceaweb_usagers",
          "deps": []
        },
        {
          "ref": "BAAC_daily_usager_id_prep",
          "deps": []
        }
      ]
    }
  },
  "outputs": {
    "main": {
      "items": [
        {
          "ref": "proceaweb_usagers_all",
          "appendMode": false
        }
      ]
    }
  },
  "versionTag": {
    "versionNumber": 1,
    "lastModifiedBy": {
      "login": "dupontlau"
    },
    "lastModifiedOn": 1536943292176
  },
  "creationTag": {
    "versionNumber": 0,
    "lastModifiedBy": {
      "login": "dupontlau"
    },
    "lastModifiedOn": 1536942242112
  },
  "tags": [],
  "checklists": {
    "checklists": []
  }
}